SDBD_pulses_amplitude_recover/__init__.py
SDBD_pulses_amplitude_recover/approximator.py
SDBD_pulses_amplitude_recover/event_detection.py
SDBD_pulses_amplitude_recover/io.py
SDBD_pulses_amplitude_recover/plotting.py
SDBD_pulses_amplitude_recover/workflow.py
sdbd_pulses_amplitude_recover-0.1.0.dist-info/licenses/LICENCE
sdbd_pulses_amplitude_recover-0.1.0.dist-info/METADATA
sdbd_pulses_amplitude_recover-0.1.0.dist-info/WHEEL
sdbd_pulses_amplitude_recover-0.1.0.dist-info/top_level.txt
sdbd_pulses_amplitude_recover-0.1.0.dist-info/RECORD
