Metadata-Version: 2.4
Name: SDBD_pulses_amplitude_recover
Version: 0.1.0
Summary: A package for recovering clipped current pulses
Author-email: Nizamov Danil <danil.nizamov@codesignal.com>
License-Expression: MIT
Project-URL: Homepage, https://github.com/reediculous/SDBD_pulses_recovery
Project-URL: Issues, https://github.com/reediculous/SDBD_pulses_recovery
Classifier: Programming Language :: Python :: 3
Classifier: Operating System :: OS Independent
Requires-Python: >=3.13
License-File: LICENCE
Dynamic: license-file
